agent_tooltree/__init__.py
agent_tooltree/core/__init__.py
agent_tooltree/core/plugin_loader.py
agent_tooltree/toolsets/__init__.py
agent_tooltree-0.0.1.dist-info/METADATA
agent_tooltree-0.0.1.dist-info/WHEEL
agent_tooltree-0.0.1.dist-info/entry_points.txt
agent_tooltree-0.0.1.dist-info/RECORD
