Metadata-Version: 2.3
Name: agent-tooltree
Version: 0.0.1
Summary: Agent ToolTree: Navigate your Agent Arsenal - A set of tools to be used by the AI agents
License: Apache-2.0
Author: Rohit S. Garud
Requires-Python: >=3.10
Classifier: License :: OSI Approved :: Apache Software License
Classifier: Programming Language :: Python :: 3
Classifier: Programming Language :: Python :: 3.10
Classifier: Programming Language :: Python :: 3.11
Classifier: Programming Language :: Python :: 3.12
Classifier: Programming Language :: Python :: 3.13
Requires-Dist: jsonschema (>=4.0.0)
Requires-Dist: pydantic (>=2.0.0)
Requires-Dist: typing-extensions (>=4.0.0)
